{
  "blogs": [
    {
      "title": "Make good content",
      "body": "It's important to create good content so you don't spread bad habits. You never know who is listening or watching!",
      "author": "yoshi",
      "id": 4
    },
    {
      "title": "Be a good person",
      "body": "People take on each other's characteristics. Be a good person.",
      "author": "mario",
      "id": 5
    },
    {
      "title": "Be happy",
      "body": "It's simple but not easy to keep this in mind. It's a daily practice!",
      "author": "mario",
      "id": 6
    },
    {
      "title": "Here's a new post",
      "body": "Hey baby, you are hot!!",
      "author": "yoshi",
      "id": 7
    }
  ]
}